{"items":[{"title":"Shortcuts.design","description":"A shortcut reference for the most important tools of designers.","link":"https://shortcuts.design/","image":"https://wwebdev-images.s3.eu-central-1.amazonaws.com/content/weekly/41/shortcutsdesign.png","tags":["Resource"]},{"title":"Omatsuri","description":"A nice collection of open-source browser tools.","link":"https://omatsuri.app/","image":"https://wwebdev-images.s3.eu-central-1.amazonaws.com/content/weekly/41/omatsuri.jpg","tags":["Resource"]},{"title":"ztext.js","description":"Easy to implement, 3D typography for the web, which works with every font.","link":"https://bennettfeely.com/ztext/","image":"https://wwebdev-images.s3.eu-central-1.amazonaws.com/content/weekly/41/ztextjs.jpg","tags":["JavaScript","Library"]},{"title":"Previewed","description":"A website to generate mockup previews on various devices.","link":"https://previewed.app/","image":"https://wwebdev-images.s3.eu-central-1.amazonaws.com/content/weekly/41/previewed.jpg","tags":["Tool"]},{"title":"Morphing SVG With react-spring","description":"A nice article by Mikael Ainalem about SVG animations in React.","link":"https://css-tricks.com/morphing-svg-with-react-spring/","image":"https://wwebdev-images.s3.eu-central-1.amazonaws.com/content/weekly/41/morphing-svg-with-reactspring.gif","tags":["Article","React"]},{"title":"Selecto.js","description":"A component that allows you to select elements in the drag area using the mouse or touch.","link":"https://github.com/daybrush/selecto","image":"https://wwebdev-images.s3.eu-central-1.amazonaws.com/content/weekly/41/selectojs.jpg","tags":["JavaScript","Library"]},{"title":"Arwes","description":"A futuristic sci-fi and cyberpunk graphical user interface framework for web apps.","link":"https://arwes.dev/","image":"https://wwebdev-images.s3.eu-central-1.amazonaws.com/content/weekly/41/arwes.jpg","tags":["CSS"]},{"title":"Meta Tags","description":"A website to edit and experiment with your content then preview how your webpage will look on Google, Facebook, Twitter, and more.","link":"https://metatags.io/","image":"https://wwebdev-images.s3.eu-central-1.amazonaws.com/content/weekly/41/meta-tags.png","tags":["Tool"]},{"title":"7 Practical Tips for Better Microcopy","description":"Some good tips for improving the copywriting of your website.","link":"https://learnuxd.io/posts/7-practical-tips-for-better-microcopy","image":"https://wwebdev-images.s3.eu-central-1.amazonaws.com/content/weekly/41/7-practical-tips-for-better-microcopy.png ","tags":["Article"]},{"title":"CSS Values","description":"A web app to search the syntax and all possible values for any valid CSS property.","link":"https://cssvalues.com/","image":"https://wwebdev-images.s3.eu-central-1.amazonaws.com/content/weekly/41/css-values.png","tags":["Tool","CSS"]},{"title":"Tailwind Ink","description":"An AI palette generator trained with the Tailwindcss colors.","link":"https://tailwind.ink/","image":"https://wwebdev-images.s3.eu-central-1.amazonaws.com/content/weekly/41/tailwind-ink.jpg","tags":["Tool"]}]}