{
  "items": [
    {
      "title": "Octomments",
      "description": "A cool alternative to Disqus for comments using GitHub issues.",
      "link": "https://ocs.now.sh/",
      "image": "https://ocs.now.sh/page/logo.jpg",
      "tags": [
        "Tool"
      ]
    },
    {
      "title": "Neumorphism",
      "description": "A CSS Code generator for Soft-UI code.",
      "link": "https://neumorphism.io/",
      "image": "https://neumorphism.io/ogImage.png",
      "tags": [
        "CSS",
        "Generator"
      ]
    },
    {
      "title": "Bit",
      "description": "Bit helps to share reusable components between different projects and applications.",
      "link": "https://bit.dev/",
      "image": "https://static.bit.dev/og-images/bit-og-img-facebook.png",
      "tags": [
        "Tool"
      ]
    },
    {
      "title": "DarkModeJS",
      "description": "A simple plugin, which helps to add a darkmode to your website.",
      "link": "https://nickdeny.github.io/darkmode-js/",
      "image": "/weekly/screenshots/darkmodejs.png",
      "tags": [
        "JavaScript",
        "Library"
      ]
    },
    {
      "title": "Full Stack Open 2019",
      "description": "An open online course by University of Helsinki on modern web development with Javascript.",
      "link": "https://fullstackopen.com/en/",
      "image": "https://fullstackopen.com/static/EYE_green_wide-0a72f74a959f54d0f3e4bb8c67f6f158.jpg",
      "tags": [
        "JavaScript"
      ]
    },
    {
      "title": "Learn CSS Positioning",
      "description": "A cool interactive article by Ahmad Shadeed about how positioning works in CSS.",
      "link": "https://ishadeed.com/article/learn-css-positioning/",
      "image": "https://ishadeed.com/assets/css-pos/img/thumb.jpg",
      "tags": [
        "Article",
        "CSS"
      ]
    },
    {
      "title": "UI/UX Design Trends for 2020",
      "description": "A list of twenty design trends, which might become more relevant in 2020.",
      "link": "https://shakuro.com/blog/ui-ux-design-trends-for-2020",
      "image": "https://blog.shakuro.com/wp-content/uploads/2019/12/ui_ux_trends_2020_.jpg",
      "tags": [
        "Article"
      ]
    },
    {
      "title": "ScrollProgressBar",
      "description": "A lightweigt library for adding a scrollbar, which displays how far an user has scrolled.",
      "link": "https://scrollprogressbar.github.io/",
      "image": "/weekly/screenshots/scrollprogressbar.png",
      "tags": [
        "Library",
        "JavaScript"
      ]
    },
    {
      "title": "Toggle dark/light theme based on your user's preferred scheme",
      "description": "An article about how to switch between the dark and the light theme based on the users preference.",
      "link": "https://gosink.in/javascript-css-toggle-dark-light-theme-based-on-your-users-preferred-scheme/",
      "image": "https://gosink.in/content/images/size/w2000/2020/02/toggle-theme.jpg",
      "tags": [
        "Article"
      ]
    }
  ]
}